django_dbml/__init__.py
django_dbml/tests.py
django_dbml/utils.py
django_dbml/management/__init__.py
django_dbml/management/commands/__init__.py
django_dbml/management/commands/dbml.py
django_dbml-0.10.0.dist-info/LICENSE
django_dbml-0.10.0.dist-info/METADATA
django_dbml-0.10.0.dist-info/WHEEL
django_dbml-0.10.0.dist-info/top_level.txt
django_dbml-0.10.0.dist-info/RECORD
